qpbenchmark/__init__.py
qpbenchmark/benchmark.py
qpbenchmark/exceptions.py
qpbenchmark/parquet_test_set.py
qpbenchmark/plot_metric.py
qpbenchmark/problem.py
qpbenchmark/problem_list.py
qpbenchmark/report.py
qpbenchmark/results.py
qpbenchmark/run.py
qpbenchmark/shgeom.py
qpbenchmark/solver_issues.py
qpbenchmark/solver_settings.py
qpbenchmark/spdlog.py
qpbenchmark/test_set.py
qpbenchmark/tolerance.py
qpbenchmark/utils.py
qpbenchmark/version.py
qpbenchmark-2.5.0.dist-info/entry_points.txt
qpbenchmark-2.5.0.dist-info/LICENSE
qpbenchmark-2.5.0.dist-info/WHEEL
qpbenchmark-2.5.0.dist-info/METADATA
qpbenchmark-2.5.0.dist-info/RECORD
