Metadata-Version: 2.1
Name: qpbenchmark
Version: 2.5.0
Summary: Benchmark for quadratic programming solvers available in Python.
Keywords: quadratic programming,benchmark,solvers,numerical optimization
Author-email: Stéphane Caron <stephane.caron@normalesup.org>
Maintainer-email: Stéphane Caron <stephane.caron@normalesup.org>
Requires-Python: >=3.9
Classifier: Development Status :: 5 - Production/Stable
Classifier: Intended Audience :: Developers
Classifier: Intended Audience :: Science/Research
Classifier: License :: OSI Approved :: Apache Software License
Classifier: Operating System :: OS Independent
Classifier: Programming Language :: Python :: 3.9
Classifier: Programming Language :: Python :: 3.10
Classifier: Programming Language :: Python :: 3.11
Classifier: Programming Language :: Python :: 3.12
Classifier: Topic :: Scientific/Engineering :: Mathematics
Requires-Dist: matplotlib >=3.6.2
Requires-Dist: numpy >=1.25.2
Requires-Dist: pandas >=1.4.3
Requires-Dist: py-cpuinfo >=9.0.0
Requires-Dist: pyarrow >=15.0.0
Requires-Dist: qpsolvers >=4.3.1
Requires-Dist: tabulate >=0.9.0
Requires-Dist: tqdm >=4.67.1
Project-URL: Changelog, https://github.com/qpsolvers/qpbenchmark/blob/main/CHANGELOG.md
Project-URL: Homepage, https://github.com/qpsolvers/qpbenchmark
Project-URL: Source, https://github.com/qpsolvers/qpbenchmark
Project-URL: Tracker, https://github.com/qpsolvers/qpbenchmark/issues
